valerie/__init__.py
valerie/admin.py
valerie/apps.py
valerie/models.py
valerie/locale/en/LC_MESSAGES/django.mo
valerie/locale/en/LC_MESSAGES/django.po
valerie/static/css/admin/settings.css
valerie/templates/admin/valerie/settings/change_form.html
valerie/templates/admin/valerie/settings/object_history.html
valerie/templatetags/__init__.py
valerie/templatetags/valerie_tags.py
django_valerie-0.2.0.dist-info/LICENCE.txt
django_valerie-0.2.0.dist-info/METADATA
django_valerie-0.2.0.dist-info/WHEEL
django_valerie-0.2.0.dist-info/top_level.txt
django_valerie-0.2.0.dist-info/RECORD
